graphiti_core_ecolink/__init__.py
graphiti_core_ecolink/edges.py
graphiti_core_ecolink/errors.py
graphiti_core_ecolink/graph_queries.py
graphiti_core_ecolink/graphiti.py
graphiti_core_ecolink/graphiti_types.py
graphiti_core_ecolink/helpers.py
graphiti_core_ecolink/nodes.py
graphiti_core_ecolink/py.typed
graphiti_core_ecolink/cross_encoder/__init__.py
graphiti_core_ecolink/cross_encoder/bge_reranker_client.py
graphiti_core_ecolink/cross_encoder/client.py
graphiti_core_ecolink/cross_encoder/gemini_reranker_client.py
graphiti_core_ecolink/cross_encoder/openai_reranker_client.py
graphiti_core_ecolink/driver/__init__.py
graphiti_core_ecolink/driver/driver.py
graphiti_core_ecolink/driver/falkordb_driver.py
graphiti_core_ecolink/driver/neo4j_driver.py
graphiti_core_ecolink/embedder/__init__.py
graphiti_core_ecolink/embedder/azure_openai.py
graphiti_core_ecolink/embedder/client.py
graphiti_core_ecolink/embedder/gemini.py
graphiti_core_ecolink/embedder/openai.py
graphiti_core_ecolink/embedder/voyage.py
graphiti_core_ecolink/llm_client/__init__.py
graphiti_core_ecolink/llm_client/anthropic_client.py
graphiti_core_ecolink/llm_client/azure_openai_client.py
graphiti_core_ecolink/llm_client/client.py
graphiti_core_ecolink/llm_client/config.py
graphiti_core_ecolink/llm_client/errors.py
graphiti_core_ecolink/llm_client/gemini_client.py
graphiti_core_ecolink/llm_client/groq_client.py
graphiti_core_ecolink/llm_client/openai_base_client.py
graphiti_core_ecolink/llm_client/openai_client.py
graphiti_core_ecolink/llm_client/openai_generic_client.py
graphiti_core_ecolink/llm_client/utils.py
graphiti_core_ecolink/models/__init__.py
graphiti_core_ecolink/models/edges/__init__.py
graphiti_core_ecolink/models/edges/edge_db_queries.py
graphiti_core_ecolink/models/nodes/__init__.py
graphiti_core_ecolink/models/nodes/node_db_queries.py
graphiti_core_ecolink/prompts/__init__.py
graphiti_core_ecolink/prompts/dedupe_edges.py
graphiti_core_ecolink/prompts/dedupe_nodes.py
graphiti_core_ecolink-0.1.4.dist-info/METADATA
graphiti_core_ecolink-0.1.4.dist-info/WHEEL
graphiti_core_ecolink-0.1.4.dist-info/licenses/LICENSE
graphiti_core_ecolink-0.1.4.dist-info/RECORD
